Workbook
Name P_DIARIA: 'Parâmetros'!$B$4
Name P_MEIA_DIARIA: 'Parâmetros'!$B$5
Name P_REFEICAO: 'Parâmetros'!$B$6
Name P_KM: 'Parâmetros'!$B$7
Name P_KM_LIVRE: 'Parâmetros'!$B$8
Name P_DIST_DIARIA: 'Parâmetros'!$B$9
Name P_H_ENG: 'Parâmetros'!$B$10
Name P_H_TST: 'Parâmetros'!$B$11
Name P_ART: 'Parâmetros'!$B$12
Name P_POSTAGEM: 'Parâmetros'!$B$13
Name P_FOLHA: 'Parâmetros'!$B$14
Name P_FOLHAS_AV: 'Parâmetros'!$B$15
Name P_LANC_H: 'Parâmetros'!$B$16
Name P_LANC_MIN: 'Parâmetros'!$B$17
Name P_REV_H: 'Parâmetros'!$B$18
Name P_ENT_H: 'Parâmetros'!$B$19
Name P_DOS_PCT: 'Parâmetros'!$B$20
Name P_DOS_LIM: 'Parâmetros'!$B$21
Name P_QUAL_VARIAS: 'Parâmetros'!$B$22
Name P_QUAL_UNICA: 'Parâmetros'!$B$23
Name P_AUSENCIA: 'Parâmetros'!$B$24
Name P_BDI: 'Parâmetros'!$B$25
Name P_DESCONTO: 'Parâmetros'!$B$26
Name T_TIPOS: 'Parâmetros'!$A$31:$A$38
Name T_HORAS: 'Parâmetros'!$B$31:$B$38
Name T_PORDIA: 'Parâmetros'!$C$31:$C$38
Name T_FIXO: 'Parâmetros'!$D$31:$D$38
Name EX_NOMES: 'Tabela de Exames'!$B$2:$B$283
Name EX_VALOR: 'Tabela de Exames'!$D$2:$D$283
Name L_EMPRESA: Levantamento!$B$3
Name L_CNPJ: Levantamento!$B$4
Name L_LOCAL: Levantamento!$B$5
Name L_DIST: Levantamento!$B$6
Name L_PERNOITE: Levantamento!$B$7
Name L_DIAS: Levantamento!$B$10
Name L_GRAU: Levantamento!$F$3
Name L_NEMP: Levantamento!$F$4
Name L_RESP: Levantamento!$F$5
Name L_DATA: Levantamento!$F$6
Name L_TIPOLAUDO: Levantamento!$F$7
Name L_TOTAL_AV: Levantamento!$F$8

Sheet Levantamento
A1: LEVANTAMENTO PARA PRECIFICAÇÃO - LTCAT / LI | H1: Preencha as células amarelas. As demais são calculadas. Ordem: GHE crescente.
A3: Empresa | D3: Grau de risco
A4: CNPJ | D4: Nº empregados
A5: Local (cidade) | D5: Responsável
A6: Distância só ida (km) | B6: 0 | D6: Data
A7: Pernoite? (Sim/Não) | B7: Não | D7: Tipo de laudo | F7: LTCAT/LI
A8: Dias em campo sugerido | B8: =MAX(1,ROUNDUP(SUM(P12:P111),0)) | D8: Total de avaliações | F8: =SUM(I12:I111)
A9: Dias em campo ajustado | D9: Horas TST de campo | F9: =SUM(L12:L111)
A10: Dias em campo (usado) | B10: =IF(B9<>"",B9,B8) | D10: Custo lab./serviços (R$) | F10: =SUM(K12:K111)
A11: Item | B11: GHE | C11: Nome do GHE | D11: Nº expostos | E11: Tipo de avaliação | F11: Agente / Exame | G11: Qtd sugerida | H11: Qtd ajustada | I11: Qtd final | J11: Valor unitário (R$) | K11: Custo lab./serviço (R$) | L11: Horas TST | M11: Folhas | N11: Observação | O11: Seq. químico | P11: Dias
A12: =IF(E12="","",ROW()-11) | G12: =IF(E12="","",IF(E12="Ruído (dosimetria)",IF(D12>P_DOS_LIM,ROUNDUP(D12*P_DOS_PCT,0),IF(N(D12)>0,1,0)),IF(E12="Ausência de risco",0,IF(OR(D12="",N(D12)>0),1,0)))) | I12: =IF(E12="","",IF(H12<>"",H12,G12)) | J12: =IF(E12="","",IF(E12="Químico (laboratório)",IFERROR(INDEX(EX_VALOR,MATCH(F12,EX_NOMES,0)),0),IF(E12="Avaliação qualitativa",IF(SUMIFS($I$12:$I$111,$E$12:$E$111,"Avaliação qualitativa")>1,P_QUAL_VARIAS,P_QUAL_UNICA),IFERROR(INDEX(T_FIXO,MATCH(E12,T_TIPOS,0)),0)))) | K12: =IF(E12="","",I12*J12) | L12: =IF(E12="","",I12*IFERROR(INDEX(T_HORAS,MATCH(E12,T_TIPOS,0)),0)) | M12: =IF(E12="","",I12*P_FOLHAS_AV) | O12: =IF(AND(E12="Químico (laboratório)",F12<>"",COUNTIFS($F$12:F12,F12,$E$12:E12,"Químico (laboratório)")=1),MAX($O$11:O11)+1,"") | P12: =IF(E12="","",IF(IFERROR(INDEX(T_PORDIA,MATCH(E12,T_TIPOS,0)),0)>0,I12/INDEX(T_PORDIA,MATCH(E12,T_TIPOS,0)),0))
A13: =IF(E13="","",ROW()-11) | G13: =IF(E13="","",IF(E13="Ruído (dosimetria)",IF(D13>P_DOS_LIM,ROUNDUP(D13*P_DOS_PCT,0),IF(N(D13)>0,1,0)),IF(E13="Ausência de risco",0,IF(OR(D13="",N(D13)>0),1,0)))) | I13: =IF(E13="","",IF(H13<>"",H13,G13)) | J13: =IF(E13="","",IF(E13="Químico (laboratório)",IFERROR(INDEX(EX_VALOR,MATCH(F13,EX_NOMES,0)),0),IF(E13="Avaliação qualitativa",IF(SUMIFS($I$12:$I$111,$E$12:$E$111,"Avaliação qualitativa")>1,P_QUAL_VARIAS,P_QUAL_UNICA),IFERROR(INDEX(T_FIXO,MATCH(E13,T_TIPOS,0)),0)))) | K13: =IF(E13="","",I13*J13) | L13: =IF(E13="","",I13*IFERROR(INDEX(T_HORAS,MATCH(E13,T_TIPOS,0)),0)) | M13: =IF(E13="","",I13*P_FOLHAS_AV) | O13: =IF(AND(E13="Químico (laboratório)",F13<>"",COUNTIFS($F$12:F13,F13,$E$12:E13,"Químico (laboratório)")=1),MAX($O$11:O12)+1,"") | P13: =IF(E13="","",IF(IFERROR(INDEX(T_PORDIA,MATCH(E13,T_TIPOS,0)),0)>0,I13/INDEX(T_PORDIA,MATCH(E13,T_TIPOS,0)),0))
A14: =IF(E14="","",ROW()-11) | G14: =IF(E14="","",IF(E14="Ruído (dosimetria)",IF(D14>P_DOS_LIM,ROUNDUP(D14*P_DOS_PCT,0),IF(N(D14)>0,1,0)),IF(E14="Ausência de risco",0,IF(OR(D14="",N(D14)>0),1,0)))) | I14: =IF(E14="","",IF(H14<>"",H14,G14)) | J14: =IF(E14="","",IF(E14="Químico (laboratório)",IFERROR(INDEX(EX_VALOR,MATCH(F14,EX_NOMES,0)),0),IF(E14="Avaliação qualitativa",IF(SUMIFS($I$12:$I$111,$E$12:$E$111,"Avaliação qualitativa")>1,P_QUAL_VARIAS,P_QUAL_UNICA),IFERROR(INDEX(T_FIXO,MATCH(E14,T_TIPOS,0)),0)))) | K14: =IF(E14="","",I14*J14) | L14: =IF(E14="","",I14*IFERROR(INDEX(T_HORAS,MATCH(E14,T_TIPOS,0)),0)) | M14: =IF(E14="","",I14*P_FOLHAS_AV) | O14: =IF(AND(E14="Químico (laboratório)",F14<>"",COUNTIFS($F$12:F14,F14,$E$12:E14,"Químico (laboratório)")=1),MAX($O$11:O13)+1,"") | P14: =IF(E14="","",IF(IFERROR(INDEX(T_PORDIA,MATCH(E14,T_TIPOS,0)),0)>0,I14/INDEX(T_PORDIA,MATCH(E14,T_TIPOS,0)),0))
A15: =IF(E15="","",ROW()-11) | G15: =IF(E15="","",IF(E15="Ruído (dosimetria)",IF(D15>P_DOS_LIM,ROUNDUP(D15*P_DOS_PCT,0),IF(N(D15)>0,1,0)),IF(E15="Ausência de risco",0,IF(OR(D15="",N(D15)>0),1,0)))) | I15: =IF(E15="","",IF(H15<>"",H15,G15)) | J15: =IF(E15="","",IF(E15="Químico (laboratório)",IFERROR(INDEX(EX_VALOR,MATCH(F15,EX_NOMES,0)),0),IF(E15="Avaliação qualitativa",IF(SUMIFS($I$12:$I$111,$E$12:$E$111,"Avaliação qualitativa")>1,P_QUAL_VARIAS,P_QUAL_UNICA),IFERROR(INDEX(T_FIXO,MATCH(E15,T_TIPOS,0)),0)))) | K15: =IF(E15="","",I15*J15) | L15: =IF(E15="","",I15*IFERROR(INDEX(T_HORAS,MATCH(E15,T_TIPOS,0)),0)) | M15: =IF(E15="","",I15*P_FOLHAS_AV) | O15: =IF(AND(E15="Químico (laboratório)",F15<>"",COUNTIFS($F$12:F15,F15,$E$12:E15,"Químico (laboratório)")=1),MAX($O$11:O14)+1,"") | P15: =IF(E15="","",IF(IFERROR(INDEX(T_PORDIA,MATCH(E15,T_TIPOS,0)),0)>0,I15/INDEX(T_PORDIA,MATCH(E15,T_TIPOS,0)),0))
A16: =IF(E16="","",ROW()-11) | G16: =IF(E16="","",IF(E16="Ruído (dosimetria)",IF(D16>P_DOS_LIM,ROUNDUP(D16*P_DOS_PCT,0),IF(N(D16)>0,1,0)),IF(E16="Ausência de risco",0,IF(OR(D16="",N(D16)>0),1,0)))) | I16: =IF(E16="","",IF(H16<>"",H16,G16)) | J16: =IF(E16="","",IF(E16="Químico (laboratório)",IFERROR(INDEX(EX_VALOR,MATCH(F16,EX_NOMES,0)),0),IF(E16="Avaliação qualitativa",IF(SUMIFS($I$12:$I$111,$E$12:$E$111,"Avaliação qualitativa")>1,P_QUAL_VARIAS,P_QUAL_UNICA),IFERROR(INDEX(T_FIXO,MATCH(E16,T_TIPOS,0)),0)))) | K16: =IF(E16="","",I16*J16) | L16: =IF(E16="","",I16*IFERROR(INDEX(T_HORAS,MATCH(E16,T_TIPOS,0)),0)) | M16: =IF(E16="","",I16*P_FOLHAS_AV) | O16: =IF(AND(E16="Químico (laboratório)",F16<>"",COUNTIFS($F$12:F16,F16,$E$12:E16,"Químico (laboratório)")=1),MAX($O$11:O15)+1,"") | P16: =IF(E16="","",IF(IFERROR(INDEX(T_PORDIA,MATCH(E16,T_TIPOS,0)),0)>0,I16/INDEX(T_PORDIA,MATCH(E16,T_TIPOS,0)),0))
A17: =IF(E17="","",ROW()-11) | G17: =IF(E17="","",IF(E17="Ruído (dosimetria)",IF(D17>P_DOS_LIM,ROUNDUP(D17*P_DOS_PCT,0),IF(N(D17)>0,1,0)),IF(E17="Ausência de risco",0,IF(OR(D17="",N(D17)>0),1,0)))) | I17: =IF(E17="","",IF(H17<>"",H17,G17)) | J17: =IF(E17="","",IF(E17="Químico (laboratório)",IFERROR(INDEX(EX_VALOR,MATCH(F17,EX_NOMES,0)),0),IF(E17="Avaliação qualitativa",IF(SUMIFS($I$12:$I$111,$E$12:$E$111,"Avaliação qualitativa")>1,P_QUAL_VARIAS,P_QUAL_UNICA),IFERROR(INDEX(T_FIXO,MATCH(E17,T_TIPOS,0)),0)))) | K17: =IF(E17="","",I17*J17) | L17: =IF(E17="","",I17*IFERROR(INDEX(T_HORAS,MATCH(E17,T_TIPOS,0)),0)) | M17: =IF(E17="","",I17*P_FOLHAS_AV) | O17: =IF(AND(E17="Químico (laboratório)",F17<>"",COUNTIFS($F$12:F17,F17,$E$12:E17,"Químico (laboratório)")=1),MAX($O$11:O16)+1,"") | P17: =IF(E17="","",IF(IFERROR(INDEX(T_PORDIA,MATCH(E17,T_TIPOS,0)),0)>0,I17/INDEX(T_PORDIA,MATCH(E17,T_TIPOS,0)),0))
A18: =IF(E18="","",ROW()-11) | G18: =IF(E18="","",IF(E18="Ruído (dosimetria)",IF(D18>P_DOS_LIM,ROUNDUP(D18*P_DOS_PCT,0),IF(N(D18)>0,1,0)),IF(E18="Ausência de risco",0,IF(OR(D18="",N(D18)>0),1,0)))) | I18: =IF(E18="","",IF(H18<>"",H18,G18)) | J18: =IF(E18="","",IF(E18="Químico (laboratório)",IFERROR(INDEX(EX_VALOR,MATCH(F18,EX_NOMES,0)),0),IF(E18="Avaliação qualitativa",IF(SUMIFS($I$12:$I$111,$E$12:$E$111,"Avaliação qualitativa")>1,P_QUAL_VARIAS,P_QUAL_UNICA),IFERROR(INDEX(T_FIXO,MATCH(E18,T_TIPOS,0)),0)))) | K18: =IF(E18="","",I18*J18) | L18: =IF(E18="","",I18*IFERROR(INDEX(T_HORAS,MATCH(E18,T_TIPOS,0)),0)) | M18: =IF(E18="","",I18*P_FOLHAS_AV) | O18: =IF(AND(E18="Químico (laboratório)",F18<>"",COUNTIFS($F$12:F18,F18,$E$12:E18,"Químico (laboratório)")=1),MAX($O$11:O17)+1,"") | P18: =IF(E18="","",IF(IFERROR(INDEX(T_PORDIA,MATCH(E18,T_TIPOS,0)),0)>0,I18/INDEX(T_PORDIA,MATCH(E18,T_TIPOS,0)),0))
A19: =IF(E19="","",ROW()-11) | G19: =IF(E19="","",IF(E19="Ruído (dosimetria)",IF(D19>P_DOS_LIM,ROUNDUP(D19*P_DOS_PCT,0),IF(N(D19)>0,1,0)),IF(E19="Ausência de risco",0,IF(OR(D19="",N(D19)>0),1,0)))) | I19: =IF(E19="","",IF(H19<>"",H19,G19)) | J19: =IF(E19="","",IF(E19="Químico (laboratório)",IFERROR(INDEX(EX_VALOR,MATCH(F19,EX_NOMES,0)),0),IF(E19="Avaliação qualitativa",IF(SUMIFS($I$12:$I$111,$E$12:$E$111,"Avaliação qualitativa")>1,P_QUAL_VARIAS,P_QUAL_UNICA),IFERROR(INDEX(T_FIXO,MATCH(E19,T_TIPOS,0)),0)))) | K19: =IF(E19="","",I19*J19) | L19: =IF(E19="","",I19*IFERROR(INDEX(T_HORAS,MATCH(E19,T_TIPOS,0)),0)) | M19: =IF(E19="","",I19*P_FOLHAS_AV) | O19: =IF(AND(E19="Químico (laboratório)",F19<>"",COUNTIFS($F$12:F19,F19,$E$12:E19,"Químico (laboratório)")=1),MAX($O$11:O18)+1,"") | P19: =IF(E19="","",IF(IFERROR(INDEX(T_PORDIA,MATCH(E19,T_TIPOS,0)),0)>0,I19/INDEX(T_PORDIA,MATCH(E19,T_TIPOS,0)),0))
A20: =IF(E20="","",ROW()-11) | G20: =IF(E20="","",IF(E20="Ruído (dosimetria)",IF(D20>P_DOS_LIM,ROUNDUP(D20*P_DOS_PCT,0),IF(N(D20)>0,1,0)),IF(E20="Ausência de risco",0,IF(OR(D20="",N(D20)>0),1,0)))) | I20: =IF(E20="","",IF(H20<>"",H20,G20)) | J20: =IF(E20="","",IF(E20="Químico (laboratório)",IFERROR(INDEX(EX_VALOR,MATCH(F20,EX_NOMES,0)),0),IF(E20="Avaliação qualitativa",IF(SUMIFS($I$12:$I$111,$E$12:$E$111,"Avaliação qualitativa")>1,P_QUAL_VARIAS,P_QUAL_UNICA),IFERROR(INDEX(T_FIXO,MATCH(E20,T_TIPOS,0)),0)))) | K20: =IF(E20="","",I20*J20) | L20: =IF(E20="","",I20*IFERROR(INDEX(T_HORAS,MATCH(E20,T_TIPOS,0)),0)) | M20: =IF(E20="","",I20*P_FOLHAS_AV) | O20: =IF(AND(E20="Químico (laboratório)",F20<>"",COUNTIFS($F$12:F20,F20,$E$12:E20,"Químico (laboratório)")=1),MAX($O$11:O19)+1,"") | P20: =IF(E20="","",IF(IFERROR(INDEX(T_PORDIA,MATCH(E20,T_TIPOS,0)),0)>0,I20/INDEX(T_PORDIA,MATCH(E20,T_TIPOS,0)),0))
A21: =IF(E21="","",ROW()-11) | G21: =IF(E21="","",IF(E21="Ruído (dosimetria)",IF(D21>P_DOS_LIM,ROUNDUP(D21*P_DOS_PCT,0),IF(N(D21)>0,1,0)),IF(E21="Ausência de risco",0,IF(OR(D21="",N(D21)>0),1,0)))) | I21: =IF(E21="","",IF(H21<>"",H21,G21)) | J21: =IF(E21="","",IF(E21="Químico (laboratório)",IFERROR(INDEX(EX_VALOR,MATCH(F21,EX_NOMES,0)),0),IF(E21="Avaliação qualitativa",IF(SUMIFS($I$12:$I$111,$E$12:$E$111,"Avaliação qualitativa")>1,P_QUAL_VARIAS,P_QUAL_UNICA),IFERROR(INDEX(T_FIXO,MATCH(E21,T_TIPOS,0)),0)))) | K21: =IF(E21="","",I21*J21) | L21: =IF(E21="","",I21*IFERROR(INDEX(T_HORAS,MATCH(E21,T_TIPOS,0)),0)) | M21: =IF(E21="","",I21*P_FOLHAS_AV) | O21: =IF(AND(E21="Químico (laboratório)",F21<>"",COUNTIFS($F$12:F21,F21,$E$12:E21,"Químico (laboratório)")=1),MAX($O$11:O20)+1,"") | P21: =IF(E21="","",IF(IFERROR(INDEX(T_PORDIA,MATCH(E21,T_TIPOS,0)),0)>0,I21/INDEX(T_PORDIA,MATCH(E21,T_TIPOS,0)),0))
A22: =IF(E22="","",ROW()-11) | G22: =IF(E22="","",IF(E22="Ruído (dosimetria)",IF(D22>P_DOS_LIM,ROUNDUP(D22*P_DOS_PCT,0),IF(N(D22)>0,1,0)),IF(E22="Ausência de risco",0,IF(OR(D22="",N(D22)>0),1,0)))) | I22: =IF(E22="","",IF(H22<>"",H22,G22)) | J22: =IF(E22="","",IF(E22="Químico (laboratório)",IFERROR(INDEX(EX_VALOR,MATCH(F22,EX_NOMES,0)),0),IF(E22="Avaliação qualitativa",IF(SUMIFS($I$12:$I$111,$E$12:$E$111,"Avaliação qualitativa")>1,P_QUAL_VARIAS,P_QUAL_UNICA),IFERROR(INDEX(T_FIXO,MATCH(E22,T_TIPOS,0)),0)))) | K22: =IF(E22="","",I22*J22) | L22: =IF(E22="","",I22*IFERROR(INDEX(T_HORAS,MATCH(E22,T_TIPOS,0)),0)) | M22: =IF(E22="","",I22*P_FOLHAS_AV) | O22: =IF(AND(E22="Químico (laboratório)",F22<>"",COUNTIFS($F$12:F22,F22,$E$12:E22,"Químico (laboratório)")=1),MAX($O$11:O21)+1,"") | P22: =IF(E22="","",IF(IFERROR(INDEX(T_PORDIA,MATCH(E22,T_TIPOS,0)),0)>0,I22/INDEX(T_PORDIA,MATCH(E22,T_TIPOS,0)),0))
A23: =IF(E23="","",ROW()-11) | G23: =IF(E23="","",IF(E23="Ruído (dosimetria)",IF(D23>P_DOS_LIM,ROUNDUP(D23*P_DOS_PCT,0),IF(N(D23)>0,1,0)),IF(E23="Ausência de risco",0,IF(OR(D23="",N(D23)>0),1,0)))) | I23: =IF(E23="","",IF(H23<>"",H23,G23)) | J23: =IF(E23="","",IF(E23="Químico (laboratório)",IFERROR(INDEX(EX_VALOR,MATCH(F23,EX_NOMES,0)),0),IF(E23="Avaliação qualitativa",IF(SUMIFS($I$12:$I$111,$E$12:$E$111,"Avaliação qualitativa")>1,P_QUAL_VARIAS,P_QUAL_UNICA),IFERROR(INDEX(T_FIXO,MATCH(E23,T_TIPOS,0)),0)))) | K23: =IF(E23="","",I23*J23) | L23: =IF(E23="","",I23*IFERROR(INDEX(T_HORAS,MATCH(E23,T_TIPOS,0)),0)) | M23: =IF(E23="","",I23*P_FOLHAS_AV) | O23: =IF(AND(E23="Químico (laboratório)",F23<>"",COUNTIFS($F$12:F23,F23,$E$12:E23,"Químico (laboratório)")=1),MAX($O$11:O22)+1,"") | P23: =IF(E23="","",IF(IFERROR(INDEX(T_PORDIA,MATCH(E23,T_TIPOS,0)),0)>0,I23/INDEX(T_PORDIA,MATCH(E23,T_TIPOS,0)),0))
... A111: =IF(E111="","",ROW()-11) | G111: =IF(E111="","",IF(E111="Ruído (dosimetria)",IF(D111>P_DOS_LIM,ROUNDUP(D111*P_DOS_PCT,0),IF(N(D111)>0,1,0)),IF(E111="Ausência de risco",0,IF(OR(D111="",N(D111)>0),1,0)))) | I111: =IF(E111="","",IF(H111<>"",H111,G111)) | J111: =IF(E111="","",IF(E111="Químico (laboratório)",IFERROR(INDEX(EX_VALOR,MATCH(F111,EX_NOMES,0)),0),IF(E111="Avaliação qualitativa",IF(SUMIFS($I$12:$I$111,$E$12:$E$111,"Avaliação qualitativa")>1,P_QUAL_VARIAS,P_QUAL_UNICA),IFERROR(INDEX(T_FIXO,MATCH(E111,T_TIPOS,0)),0)))) | K111: =IF(E111="","",I111*J111) | L111: =IF(E111="","",I111*IFERROR(INDEX(T_HORAS,MATCH(E111,T_TIPOS,0)),0)) | M111: =IF(E111="","",I111*P_FOLHAS_AV) | O111: =IF(AND(E111="Químico (laboratório)",F111<>"",COUNTIFS($F$12:F111,F111,$E$12:E111,"Químico (laboratório)")=1),MAX($O$11:O110)+1,"") | P111: =IF(E111="","",IF(IFERROR(INDEX(T_PORDIA,MATCH(E111,T_TIPOS,0)),0)>0,I111/INDEX(T_PORDIA,MATCH(E111,T_TIPOS,0)),0))
A113: Como preencher: uma linha por GHE x agente. Para químico de laboratório escolha o exame na lista (nome igual ao da Tabela de Exames). Para radiação, frio, umidade, biológico e químicos sem exame use "Avaliação qualitativa". GHE sem risco: "Ausência de risco" (não gera custo). "Qtd ajustada" sobrepõe a sugerida.

Sheet Precificação
A1: ="SESI - DR/GOIÁS - "&YEAR(IF(L_DATA="",TODAY(),L_DATA)) | AD1: Responsável: | AH1: =L_RESP
A2: Planilha de Custos: | N2: =L_TIPOLAUDO | AD2: Data: | AF2: =IF(L_DATA="",TODAY(),L_DATA)
A4: Empresa: | D4: =L_EMPRESA&IF(L_CNPJ="",""," - CNPJ "&L_CNPJ) | R4: Local: | T4: =L_LOCAL | AA4: Grau de Risco: | AE4: =IF(L_GRAU="","",L_GRAU) | AF4: N.º empregados: | AJ4: =IF(L_NEMP="","",L_NEMP)
A6: 1 - DESPESAS COM COLABORADORES | R6: 3 - MATERIAL DE EXPEDIENTE E OUTROS
A7: Levantamento de Dados | H7: N.º de Dias | K7: Custo/dia | N7: Total | R7: Especificação | AC7: Quant. | AF7: Valor Unit. | AI7: Total
A8: Diária Completa | H8: =IF(L_PERNOITE="Sim",L_DIAS,0) | K8: =P_DIARIA | N8: =H8*K8 | R8: ART - CREA | AC8: 1 | AF8: =P_ART | AI8: =AC8*AF8
A9: Meia Diária | H9: =IF(AND(L_PERNOITE<>"Sim",L_DIST>P_DIST_DIARIA),L_DIAS,0) | K9: =P_MEIA_DIARIA | N9: =H9*K9 | R9: Postagem para Amostra | AC9: =IF(SUMIFS(Levantamento!$I$12:$I$111,Levantamento!$E$12:$E$111,"Químico (laboratório)")>0,2,0) | AF9: =P_POSTAGEM | AI9: =AC9*AF9
K10: Custos (1) | N10: =SUM(N8:P9) | R10: Material administrativo (folha de papel + impressão) | AC10: =SUM(Levantamento!M12:M111) | AF10: =P_FOLHA | AI10: =AC10*AF10
AF11: Custos (6) | AI11: =SUM(AI8:AK10)
A12: Levantamento de Dados | H12: N.º de Horas Totais | K12: Custo/hora | N12: Total
A13: Levantamento de Dados Engenheiro | H13: 0 | K13: =P_H_ENG | N13: =K13*H13 | R13: 4 - OUTROS TIPOS DE SERVIÇOS
A14: Levantamento de Dados Tec. Segurança | H14: =SUM(Levantamento!L12:L111) | K14: =P_H_TST | N14: =K14*H14 | R14: Descrição | AC14: Quantidade | AF14: Valor Unit. | AI14: Valor Total
A15: Lançamento de Dados Tec. Segurança | H15: =MAX(P_LANC_MIN,L_TOTAL_AV*P_LANC_H) | K15: =P_H_TST | N15: =K15*H15 | R15: Dosimetria de ruído | AC15: =SUMIFS(Levantamento!$I$12:$I$111,Levantamento!$E$12:$E$111,"Ruído (dosimetria)") | AF15: =IFERROR(INDEX(T_FIXO,MATCH("Ruído (dosimetria)",T_TIPOS,0)),0) | AI15: =AC15*AF15
A16: Revisão de Relatório Engenheiro | H16: =P_REV_H | K16: =P_H_ENG | N16: =K16*H16 | R16: Avaliação de calor (IBUTG) | AC16: =SUMIFS(Levantamento!$I$12:$I$111,Levantamento!$E$12:$E$111,"Calor (IBUTG)") | AF16: =IFERROR(INDEX(T_FIXO,MATCH("Calor (IBUTG)",T_TIPOS,0)),0) | AI16: =AC16*AF16
A17: Entrega de Relatório Engenheiro | H17: =P_ENT_H | K17: =P_H_ENG | N17: =H17*K17 | R17: Vibração de corpo inteiro | AC17: =SUMIFS(Levantamento!$I$12:$I$111,Levantamento!$E$12:$E$111,"Vibração corpo inteiro") | AF17: =IFERROR(INDEX(T_FIXO,MATCH("Vibração corpo inteiro",T_TIPOS,0)),0) | AI17: =AC17*AF17
K18: Custos (2) | N18: =SUM(N13:P17) | R18: Vibração de mãos e braços | AC18: =SUMIFS(Levantamento!$I$12:$I$111,Levantamento!$E$12:$E$111,"Vibração mãos e braços") | AF18: =IFERROR(INDEX(T_FIXO,MATCH("Vibração mãos e braços",T_TIPOS,0)),0) | AI18: =AC18*AF18
R19: Avaliação qualitativa | AC19: =SUMIFS(Levantamento!$I$12:$I$111,Levantamento!$E$12:$E$111,"Avaliação qualitativa") | AF19: =IF(AC19>0,SUMIFS(Levantamento!$K$12:$K$111,Levantamento!$E$12:$E$111,"Avaliação qualitativa")/AC19,0) | AI19: =AC19*AF19
A20: Levantamento de Dados | H20: N.º Horas Extras (50%) | K20: Custo/hora | N20: Total | R20: Laudo de Periculosidade (cargos) | AC20: =SUMIFS(Levantamento!$I$12:$I$111,Levantamento!$E$12:$E$111,"Periculosidade (por cargo)") | AF20: =IFERROR(INDEX(T_FIXO,MATCH("Periculosidade (por cargo)",T_TIPOS,0)),0) | AI20: =AC20*AF20
A21: Engenheiro | H21: 0 | K21: =(K13*50%) | N21: =H21*K21 | R21: =IFERROR(INDEX(Levantamento!$F$12:$F$111,MATCH(1,Levantamento!$O$12:$O$111,0)),"") | AC21: =IF(R21="","",SUMIFS(Levantamento!$I$12:$I$111,Levantamento!$F$12:$F$111,R21,Levantamento!$E$12:$E$111,"Químico (laboratório)")) | AF21: =IF(R21="","",INDEX(Levantamento!$J$12:$J$111,MATCH(1,Levantamento!$O$12:$O$111,0))) | AI21: =IF(R21="",0,AC21*AF21)
A22: Técnico de Segurança | H22: 0 | K22: =(K14*50%) | N22: =K22*H22 | R22: =IFERROR(INDEX(Levantamento!$F$12:$F$111,MATCH(2,Levantamento!$O$12:$O$111,0)),"") | AC22: =IF(R22="","",SUMIFS(Levantamento!$I$12:$I$111,Levantamento!$F$12:$F$111,R22,Levantamento!$E$12:$E$111,"Químico (laboratório)")) | AF22: =IF(R22="","",INDEX(Levantamento!$J$12:$J$111,MATCH(2,Levantamento!$O$12:$O$111,0))) | AI22: =IF(R22="",0,AC22*AF22)
K23: Custos (3) | N23: =SUM(N21:P22) | R23: =IFERROR(INDEX(Levantamento!$F$12:$F$111,MATCH(3,Levantamento!$O$12:$O$111,0)),"") | AC23: =IF(R23="","",SUMIFS(Levantamento!$I$12:$I$111,Levantamento!$F$12:$F$111,R23,Levantamento!$E$12:$E$111,"Químico (laboratório)")) | AF23: =IF(R23="","",INDEX(Levantamento!$J$12:$J$111,MATCH(3,Levantamento!$O$12:$O$111,0))) | AI23: =IF(R23="",0,AC23*AF23)
R24: =IFERROR(INDEX(Levantamento!$F$12:$F$111,MATCH(4,Levantamento!$O$12:$O$111,0)),"") | AC24: =IF(R24="","",SUMIFS(Levantamento!$I$12:$I$111,Levantamento!$F$12:$F$111,R24,Levantamento!$E$12:$E$111,"Químico (laboratório)")) | AF24: =IF(R24="","",INDEX(Levantamento!$J$12:$J$111,MATCH(4,Levantamento!$O$12:$O$111,0))) | AI24: =IF(R24="",0,AC24*AF24)
A25: Levantamento de Dados | H25: N.º Horas Extras (100%) | K25: Custo/hora | N25: Total | R25: =IFERROR(INDEX(Levantamento!$F$12:$F$111,MATCH(5,Levantamento!$O$12:$O$111,0)),"") | AC25: =IF(R25="","",SUMIFS(Levantamento!$I$12:$I$111,Levantamento!$F$12:$F$111,R25,Levantamento!$E$12:$E$111,"Químico (laboratório)")) | AF25: =IF(R25="","",INDEX(Levantamento!$J$12:$J$111,MATCH(5,Levantamento!$O$12:$O$111,0))) | AI25: =IF(R25="",0,AC25*AF25)
A26: Engenheiro | H26: 0 | K26: =(K13*100%) | N26: =H26*K26 | R26: =IFERROR(INDEX(Levantamento!$F$12:$F$111,MATCH(6,Levantamento!$O$12:$O$111,0)),"") | AC26: =IF(R26="","",SUMIFS(Levantamento!$I$12:$I$111,Levantamento!$F$12:$F$111,R26,Levantamento!$E$12:$E$111,"Químico (laboratório)")) | AF26: =IF(R26="","",INDEX(Levantamento!$J$12:$J$111,MATCH(6,Levantamento!$O$12:$O$111,0))) | AI26: =IF(R26="",0,AC26*AF26)
A27: Técnico de Segurança | H27: 0 | K27: =(K14*100%) | N27: =K27*H27 | R27: =IFERROR(INDEX(Levantamento!$F$12:$F$111,MATCH(7,Levantamento!$O$12:$O$111,0)),"") | AC27: =IF(R27="","",SUMIFS(Levantamento!$I$12:$I$111,Levantamento!$F$12:$F$111,R27,Levantamento!$E$12:$E$111,"Químico (laboratório)")) | AF27: =IF(R27="","",INDEX(Levantamento!$J$12:$J$111,MATCH(7,Levantamento!$O$12:$O$111,0))) | AI27: =IF(R27="",0,AC27*AF27)
K28: Custos (4) | N28: =SUM(N26:P27) | R28: =IFERROR(INDEX(Levantamento!$F$12:$F$111,MATCH(8,Levantamento!$O$12:$O$111,0)),"") | AC28: =IF(R28="","",SUMIFS(Levantamento!$I$12:$I$111,Levantamento!$F$12:$F$111,R28,Levantamento!$E$12:$E$111,"Químico (laboratório)")) | AF28: =IF(R28="","",INDEX(Levantamento!$J$12:$J$111,MATCH(8,Levantamento!$O$12:$O$111,0))) | AI28: =IF(R28="",0,AC28*AF28)
R29: =IFERROR(INDEX(Levantamento!$F$12:$F$111,MATCH(9,Levantamento!$O$12:$O$111,0)),"") | AC29: =IF(R29="","",SUMIFS(Levantamento!$I$12:$I$111,Levantamento!$F$12:$F$111,R29,Levantamento!$E$12:$E$111,"Químico (laboratório)")) | AF29: =IF(R29="","",INDEX(Levantamento!$J$12:$J$111,MATCH(9,Levantamento!$O$12:$O$111,0))) | AI29: =IF(R29="",0,AC29*AF29)
R30: =IFERROR(INDEX(Levantamento!$F$12:$F$111,MATCH(10,Levantamento!$O$12:$O$111,0)),"") | AC30: =IF(R30="","",SUMIFS(Levantamento!$I$12:$I$111,Levantamento!$F$12:$F$111,R30,Levantamento!$E$12:$E$111,"Químico (laboratório)")) | AF30: =IF(R30="","",INDEX(Levantamento!$J$12:$J$111,MATCH(10,Levantamento!$O$12:$O$111,0))) | AI30: =IF(R30="",0,AC30*AF30)
R31: =IFERROR(INDEX(Levantamento!$F$12:$F$111,MATCH(11,Levantamento!$O$12:$O$111,0)),"") | AC31: =IF(R31="","",SUMIFS(Levantamento!$I$12:$I$111,Levantamento!$F$12:$F$111,R31,Levantamento!$E$12:$E$111,"Químico (laboratório)")) | AF31: =IF(R31="","",INDEX(Levantamento!$J$12:$J$111,MATCH(11,Levantamento!$O$12:$O$111,0))) | AI31: =IF(R31="",0,AC31*AF31)
A32: 2 - DESPESAS C/ TRANSPORTE e ALMENTAÇÃO | R32: =IFERROR(INDEX(Levantamento!$F$12:$F$111,MATCH(12,Levantamento!$O$12:$O$111,0)),"") | AC32: =IF(R32="","",SUMIFS(Levantamento!$I$12:$I$111,Levantamento!$F$12:$F$111,R32,Levantamento!$E$12:$E$111,"Químico (laboratório)")) | AF32: =IF(R32="","",INDEX(Levantamento!$J$12:$J$111,MATCH(12,Levantamento!$O$12:$O$111,0))) | AI32: =IF(R32="",0,AC32*AF32)
A33: Meios de Transporte | H33: Quant. | K33: Valor | N33: Total | R33: =IFERROR(INDEX(Levantamento!$F$12:$F$111,MATCH(13,Levantamento!$O$12:$O$111,0)),"") | AC33: =IF(R33="","",SUMIFS(Levantamento!$I$12:$I$111,Levantamento!$F$12:$F$111,R33,Levantamento!$E$12:$E$111,"Químico (laboratório)")) | AF33: =IF(R33="","",INDEX(Levantamento!$J$12:$J$111,MATCH(13,Levantamento!$O$12:$O$111,0))) | AI33: =IF(R33="",0,AC33*AF33)
A34: Veículo Alugado | H34: 0 | K34: 0 | N34: =H34*K34 | R34: =IF(MAX(Levantamento!$O$12:$O$111)>13,"Demais exames de laboratório (ver aba Levantamento)","") | AI34: =SUMIFS(Levantamento!$K$12:$K$111,Levantamento!$E$12:$E$111,"Químico (laboratório)")-SUM(AI21:AK33)
A35: Km Rodado | H35: =IF(L_DIST*2<=P_KM_LIVRE,0,IF(L_PERNOITE="Sim",L_DIST*2,L_DIST*2*L_DIAS)) | K35: =P_KM | N35: =H35*K35 | AF35: Custos (7) | AI35: =SUM(AI15:AK34)
A36: Outros (Alimentação, Passagens Etc) | H36: =IF(L_DIST<=P_DIST_DIARIA,L_DIAS,0) | K36: =P_REFEICAO | N36: =H36*K36
A37: Outros (Alimentação, Passagens Etc) | K37: Custos (5) | N37: =SUM(N34:P36) | R37: 5 - Custos Totais (1+2+3+4+5+6+7) | AI37: =N10+N18+N23+N28+N37+AI11+AI35
R38: 6 - Bonificação de Despesas Indiretas - BDI (%) | AF38: =P_BDI | AI38: =AI37*AF38
A39: Observaões: | G39: ="Avaliações: "&L_TOTAL_AV&" | Dias em campo: "&L_DIAS&" | Horas TST campo: "&H14&IF(L_TOTAL_AV=0," | LAUDO DE AUSÊNCIA DE RISCO (valor fechado)","") | R39: 7 - Desconto Exclusivo (%) | AF39: =P_DESCONTO | AI39: =AF39*(AI37+AI38)
R40: 8 - Margem Final | AF40: =(AI41/AI37)-1
R41: 9 - Valor total da proposta | AI41: =IF(L_TOTAL_AV=0,P_AUSENCIA,AI37+AI38-AI39)
A42: Nome do Responsável: | G42: =L_RESP

Sheet Parâmetros
A1: PARÂMETROS DE PRECIFICAÇÃO - LTCAT / LI / LP
A2: Células amarelas: valores que você pode alterar. Todas as fórmulas das outras abas usam estes valores.
A3: Parâmetro | B3: Valor | C3: Observação
A4: Diária completa (R$/dia) | B4: 250 | C4: Com pernoite.
A5: Meia diária (R$/dia) | B5: 90 | C5: Acima de 150 km (ida) voltando no mesmo dia.
A6: Refeição / ajuda de custo (R$/dia) | B6: 55 | C6: Até 150 km (ida). Laudo paga o almoço independente do km.
A7: Km rodado (R$/km) | B7: 2 | C7: Valor por km (ida e volta).
A8: Ida e volta sem cobrança de deslocamento (até km) | B8: 50 | C8: Se ida + volta der até este valor, não cobra km.
A9: Distância (ida) a partir da qual paga diária (km) | B9: 150 | C9: Acima disto: meia diária (mesmo dia) ou diária completa (pernoite).
A10: Hora Engenheiro (R$/h) | B10: 61.19
A11: Hora Técnico de Segurança (R$/h) | B11: 24.5
A12: ART - CREA (R$) | B12: 250
A13: Postagem de amostra (R$/envio) | B13: 70 | C13: SP-GO e GO-SP. Sugestão automática: 2 envios quando há químico de laboratório.
A14: Folha de papel + impressão (R$/folha) | B14: 0.65
A15: Folhas por avaliação | B15: 10 | C15: Material administrativo = nº de avaliações x 10.
A16: Lançamento de dados: horas TST por avaliação | B16: 1
A17: Lançamento de dados: horas mínimas | B17: 5
A18: Revisão de relatório: horas Engenheiro | B18: 5
A19: Entrega de relatório: horas Engenheiro | B19: 0
A20: Dosimetria: % dos expostos do GHE | B20: 0.2
A21: Dosimetria: aplica o % quando expostos acima de | B21: 9 | C21: Até 9 expostos: 1 dosimetria por GHE.
A22: Avaliação qualitativa (R$) quando há mais de uma | B22: 150
A23: Avaliação qualitativa (R$) quando é a única | B23: 300
A24: Laudo de ausência de risco (valor fechado, R$) | B24: 1500 | C24: Vale para LTCAT e LI quando não há nenhuma avaliação.
A25: BDI (%) | B25: 0.3
A26: Desconto exclusivo (%) | B26: 0
A29: TIPOS DE AVALIAÇÃO
A30: Tipo de avaliação | B30: Horas TST por avaliação | C30: Avaliações por dia (campo) | D30: Valor unitário fixo (R$) | E30: Regra de quantidade
A31: Ruído (dosimetria) | B31: 10 | C31: 6 | D31: 0 | E31: 20% dos expostos do GHE quando acima de 9; senão 1. Custo entra nas horas técnicas.
A32: Calor (IBUTG) | B32: 4 | C32: 2 | D32: 0 | E32: 1 por GHE. Custo entra nas horas técnicas (4 h por medição).
A33: Vibração corpo inteiro | B33: 5 | C33: 6 | D33: 300 | E33: 1 por GHE. Preço fixo + horas técnicas.
A34: Vibração mãos e braços | B34: 5 | C34: 6 | D34: 300 | E34: 1 por GHE. Preço fixo + horas técnicas.
A35: Químico (laboratório) | B35: 2 | C35: 5 | D35: 0 | E35: 1 amostrador por GHE. Preço da Tabela de Exames 2026/2027. Varredura quando compensar.
A36: Avaliação qualitativa | B36: 1 | C36: 10 | D36: 0 | E36: R$ 150 por avaliação; R$ 300 quando é a única avaliação do orçamento.
A37: Ausência de risco | B37: 0 | C37: 0 | D37: 0 | E37: Não gera avaliação. Se o laudo inteiro for de ausência, vale o valor fechado (Parâmetros).
A38: Periculosidade (por cargo) | B38: 0 | C38: 0 | D38: 1500 | E38: Laudo de Periculosidade: R$ 1.500 por cargo na região; quando são muitos cargos, R$ 800 (mude o valor aqui). Fora da cidade, somar km, diárias e ART.
A41: Fonte dos valores: Planilha de Custos SESI DR/GO 2026, anotações de precificação da Central de SST e 3º Termo Aditivo Uniscientific (25/06/2026).

Sheet Tabela de Exames
A1: Item | B1: Descrição do Agente / Exame | C1: Valor 2025/2026 (R$) | D1: Valor 2026/2027 (R$) | E1: Variação
A2: 1 | B2: 1,3-Butadieno | C2: 176.4 | D2: 176.4 | E2: 0
A3: 2 | B3: 1,4-Dioxano | C3: 258.72 | D3: 258.72 | E3: 0
A4: 3 | B4: 1-Metil naftaleno e 2-Metil naftaleno | C4: 194.04 | D4: 194.04 | E4: 0
A5: 4 | B5: 1-Metoxi-2-propanol | C5: 97.2 | D5: 115 | E5: 0.18
A6: 5 | B6: 2,4-D | C6: 305.76 | D6: 305.76 | E6: 0
A7: 6 | B7: 2-Butóxi etanol (EGBE) | C7: 88.2 | D7: 94 | E7: 0.07
A8: 7 | B8: 2-Cianoacrilato de etila | C8: 383.67 | D8: 383.67 | E8: 0
A9: 8 | B9: 2-Etoxietanol | C9: 88.2 | D9: 94 | E9: 0.07
A10: 9 | B10: 2-Metoxietanol | C10: 99.96 | D10: 105 | E10: 0.05
A11: 10 | B11: 2-N-Dibutilaminoetanol | C11: 88.2 | D11: 94 | E11: 0.07
A12: 11 | B12: 2-Propanol | C12: 88.2 | D12: 94 | E12: 0.07
A13: 12 | B13: 4,4-Metileno-bis-(2-cloroanilina) (MOCA) | C13: 123.48 | D13: 130 | E13: 0.05
... A283: 282 | B283: Zircônio e compostos, como Zr | C283: 76.44 | D283: 76.44 | E283: 0
A285: Fonte: 3º Termo Aditivo ao Contrato 101/2023 SESI-GO x Uniscientific Group Laboratório, Goiânia, 25/06/2026. Vigência 26/06/2026 a 25/06/2027. A coluna "Valor 2026/2027" é a usada na precificação.
